{"title":"2023年U20世青赛斯洛伐克队大名单简介","uid":"5511d62fc9e182ca13ea7e201504319f","slug":"2023-u20-world-players","date":"2022-04-30T03:23:40.000Z","updated":"2023-05-02T04:54:59.204Z","comments":true,"path":"api/articles/2023-u20-world-players.json","keywords":null,"cover":"https://i.im.ge/2021/10/12/olZ2DF.jpg","content":"<p>2023年世青赛其他专题：<a href=\"/post/2023-u20-world-preview\">前瞻</a></p>\n<p>2022年欧青赛专题：<a href=\"/post/2022-u19-euro\">球员简介及前瞻</a>、<a href=\"/post/2022-u19-euro-matches\">比赛赛况</a></p>\n<blockquote><span class=\"custom-blockquote-svg\"><svg width=\"24\" height=\"24\" viewBox=\"0 0 24 24\" fill=\"\" xmlns=\"http://www.w3.org/2000/svg\" data-reactroot=\"\">\n<path fill=\"\" d=\"M22 12C22 6.5 17.5 2 12 2C6.5 2 2 6.5 2 12C2 17.5 6.5 22 12 22C13.8 22 15.5 21.5 17 20.6L22 22L20.7 17C21.5 15.5 22 13.8 22 12Z\" undefined=\"1\"></path>\n<path fill=\"\" d=\"M15.97 11.5H16.04C17.12 11.5 18 12.38 18 13.47V13.53C18 14.62 17.12 15.5 16.03 15.5H15.96C14.88 15.5 14 14.62 14 13.53V13.46C14 12.38 14.88 11.5 15.97 11.5Z\" undefined=\"1\"></path>\n<path fill=\"\" d=\"M7.97 11.5H8.04C9.12 11.5 10 12.38 10 13.47V13.53C10 14.62 9.12 15.5 8.03 15.5H7.97C6.88 15.5 6 14.62 6 13.53V13.46C6 12.38 6.88 11.5 7.97 11.5Z\" undefined=\"1\"></path>\n<path stroke-linejoin=\"round\" stroke-linecap=\"round\" stroke-miterlimit=\"10\" stroke-width=\"2\" stroke=\"\" d=\"M17 8.5C15.23 8.97 14.07 10.84 14.01 13.27C14 13.33 14 13.4 14 13.47V13.5\"></path>\n<path stroke-linejoin=\"round\" stroke-linecap=\"round\" stroke-miterlimit=\"10\" stroke-width=\"2\" stroke=\"\" d=\"M9 8.5C7.23 8.97 6.07 10.84 6.01 13.27C6 13.33 6 13.4 6 13.47V13.5\"></path>\n<path stroke-linejoin=\"round\" stroke-linecap=\"round\" stroke-miterlimit=\"10\" stroke-width=\"2\" stroke=\"\" d=\"M15.97 11.5H16.04C17.12 11.5 18 12.38 18 13.47V13.53C18 14.62 17.12 15.5 16.03 15.5H15.96C14.88 15.5 14 14.62 14 13.53V13.46C14 12.38 14.88 11.5 15.97 11.5Z\"></path>\n<path stroke-linejoin=\"round\" stroke-linecap=\"round\" stroke-miterlimit=\"10\" stroke-width=\"2\" stroke=\"\" d=\"M7.97 11.5H8.04C9.12 11.5 10 12.38 10 13.47V13.53C10 14.62 9.12 15.5 8.03 15.5H7.97C6.88 15.5 6 14.62 6 13.53V13.46C6 12.38 6.88 11.5 7.97 11.5Z\"></path>\n</svg>\n</span><p>最后更新： 2022年4月30日<br>本文写于斯洛伐克队大名单公布之前，所列球员是否能够入选纯属猜测。大名单正式公布后将会进行补充，敬请期待！</p></blockquote>\n<h2 id=\"前言\"><a href=\"#前言\" class=\"headerlink\" title=\"前言\"></a>前言</h2><p>每次介绍斯洛伐克的年轻球员，我的心里都是矛盾的。因为一个青训水平弱势（虽然数量可能强势）的国家，本身是缺少话语权的。但是在当今社交媒体宣传的时代，讨论不能完全没有，否则就是自动宣示“我国无宝”。但是马上面临大赛的检验，又不敢写过头。否则就会重演小时候看《西游记》的经典片段：你觉得是宝，人家觉得是“破烂流丢一口钟”，打开一看还真是。而写得太弱势，又会让人觉得你对球队缺少感情。</p>\n<p>这篇文章会尽量客观地逐一介绍斯洛伐克U20集训大名单里的球员。当然，笔者也有个人喜好，对不同球员的了解程度也有多寡之分，对足球的理解也有限，因此每个球员获得的篇幅和文字的质量可能会相差不少，请大家多多指正。</p>\n<p>最终的21人名单应该与欧青赛20人名单差距在5人之内。名单出现变化的主要原因，还是欧青赛之后2003年出生的球员超龄，无法继续踢U19连胜。有些球员在成年联赛（特别是斯超和斯甲）中很难获得机会，就会被出场机会多的球员替代。这些球员大多所属在斯甲有预备队或卫星队的斯超球队。</p>\n<p>:::details 斯洛伐克U20国家队集训名单（2023年5月26日）</p>\n<p>注年份者为跳级球员。高亮有斯超经验。</p>\n<table>\n<thead>\n<tr>\n<th>球员</th>\n<th>俱乐部</th>\n<th>备注</th>\n</tr>\n</thead>\n<tbody><tr>\n<td>Filip Baláž 巴拉日</td>\n<td>班斯卡-比斯特里察杜克拉</td>\n<td>门将</td>\n</tr>\n<tr>\n<td><strong>Adam Hrdina 赫尔季纳</strong> （2004）</td>\n<td>布拉迪斯拉发斯拉夫人</td>\n<td>门将</td>\n</tr>\n<tr>\n<td><strong>Samuel Kopásek 科帕塞克</strong></td>\n<td>日利纳</td>\n<td>右/左边后卫</td>\n</tr>\n<tr>\n<td><strong>Jakub Luka 卢卡</strong></td>\n<td>鲁容贝罗克</td>\n<td>中卫</td>\n</tr>\n<tr>\n<td><strong>Nicolas Šikula 希库拉</strong></td>\n<td>波德布雷佐瓦</td>\n<td>右/左边后卫</td>\n</tr>\n<tr>\n<td><strong>Marek Ujlaky 乌伊拉基</strong></td>\n<td>特尔纳瓦斯巴达克</td>\n<td>中卫</td>\n</tr>\n<tr>\n<td><strong>Sebastián Kóša 科沙</strong></td>\n<td>特尔纳瓦斯巴达克</td>\n<td>中卫</td>\n</tr>\n<tr>\n<td><strong>Šimon Mičuda 米楚达</strong>（2004）</td>\n<td>特伦钦</td>\n<td>右边后卫</td>\n</tr>\n<tr>\n<td><strong>Dominik Hollý 霍利</strong></td>\n<td>特伦钦</td>\n<td>中场中路</td>\n</tr>\n<tr>\n<td><strong>Artur Gajdoš 加伊多什</strong>（2004）</td>\n<td>特伦钦</td>\n<td>中场中路</td>\n</tr>\n<tr>\n<td><strong>Gabriel Halabrín 哈拉布林</strong></td>\n<td>塞尼察</td>\n<td>中场中路</td>\n</tr>\n<tr>\n<td>Maté Szolgai 马泰·索尔戈伊</td>\n<td>多瑙斯特雷达</td>\n<td>中场中路</td>\n</tr>\n<tr>\n<td><strong>Dominik Šnajder 施奈德</strong></td>\n<td>日利纳</td>\n<td>中场中路</td>\n</tr>\n<tr>\n<td><strong>Mário Sauer 马里奥·萨乌尔</strong> （2004）</td>\n<td>日利纳</td>\n<td>中场中路</td>\n</tr>\n<tr>\n<td>Martin Oravec 马丁·奥拉维茨</td>\n<td>日利纳</td>\n<td>中场中路</td>\n</tr>\n<tr>\n<td>Viktor Sliacký 斯利亚茨基</td>\n<td>彼得扎尔卡</td>\n<td>边锋/中场中路</td>\n</tr>\n<tr>\n<td>Martin Mišovič 米绍维奇 （2004）</td>\n<td>布拉迪斯拉发斯拉夫人</td>\n<td>边锋</td>\n</tr>\n<tr>\n<td><strong>Timotej Jambor 亚姆博尔</strong></td>\n<td>日利纳</td>\n<td>中锋/中场中路</td>\n</tr>\n<tr>\n<td><strong>Adam Gaži 加希</strong></td>\n<td>特伦钦</td>\n<td>边锋</td>\n</tr>\n<tr>\n<td><strong>Adam Griger 格里格尔</strong>（2004）</td>\n<td>LASK林茨</td>\n<td>中锋/边锋</td>\n</tr>\n</tbody></table>\n<h2 id=\"大名单介绍\"><a href=\"#大名单介绍\" class=\"headerlink\" title=\"大名单介绍\"></a>大名单介绍</h2><h3 id=\"门将\"><a href=\"#门将\" class=\"headerlink\" title=\"门将\"></a>门将</h3><h4 id=\"菲利普·巴拉日-Filip-Balaz\"><a href=\"#菲利普·巴拉日-Filip-Balaz\" class=\"headerlink\" title=\"菲利普·巴拉日 Filip Baláž\"></a>菲利普·巴拉日 Filip Baláž</h4><p><a href=\"https://www.transfermarkt.us/filip-balaz/profil/spieler/720767\">Transfermarkt</a></p>\n<p>俱乐部：班斯卡-比斯特里察杜克拉（斯超）、下库宾（斯甲）</p>\n<p>巴拉日从U17开始就是这一年龄段国家队的常客。他曾在2021年10月1-0零封葡萄牙，作出多次漂亮的扑救。欧青赛正赛上他在最艰难的头两场比赛（法国、意大利）担任首发，可以说已经竭尽全力帮助球队挽尊。</p>\n<p>不过随着U19周期结束，巴拉日的母队升上斯超，一线队无法给他出场机会。因此他要么出现在一线队的替补席，要么在卫星队下库宾首发，但主力位置也没有保障。此外，由于下库宾是斯甲联赛的弱旅，巴拉日的纸面数据不算好看，但实力还是不容置疑的。</p>\n<p>轶闻：2021年4月，当时刚过了18岁生日两天的巴拉日临危受命，在斯洛伐克杯四分之一决赛首发。结果他与队友联袂献上了精彩的反击战，最终3-2淘汰有意问鼎斯超的多瑙斯特雷达。之后他还在半决赛次回合首发。</p>\n<h4 id=\"亚当·赫尔季纳-Adam-Hrdina\"><a href=\"#亚当·赫尔季纳-Adam-Hrdina\" class=\"headerlink\" title=\"亚当·赫尔季纳 Adam Hrdina\"></a>亚当·赫尔季纳 Adam Hrdina</h4><p><a href=\"https://www.transfermarkt.us/adam-hrdina/profil/spieler/726664\">Transfermarkt</a></p>\n<p>俱乐部：布拉迪斯拉发斯拉夫人预备队/U19</p>\n<p>跳级生赫尔季纳在2003和2004两个年龄段都有稳定的出场机会。在刚刚结束的U19欧青赛预选赛（2004年龄段）上，赫尔季纳表现出色，帮助斯洛伐克U19在关键战中击败爱尔兰、逼平希腊。这赛季他也在斯拉夫人的预备队获得了一定的斯甲联赛出场机会，可惜虽然球队战绩不错，他的失球也不多，但是没有零封。</p>\n<p>轶闻：赫尔季纳的爸爸米洛斯拉夫是布拉迪斯拉发斯拉夫人一线队的门将教练。其姓氏“赫尔季纳”在斯洛伐克语里的意思是“英雄”。</p>\n<p><img src=\"https://i.im.ge/2022/06/17/r4m33T.jpg\" alt=\"左到右：巴拉日、赫尔季纳、丹科\"><span class=\"image-caption\">左到右：巴拉日、赫尔季纳、丹科</span></p>\n<h3 id=\"萨穆埃尔·贝拉尼克-Samuel-Belanik\"><a href=\"#萨穆埃尔·贝拉尼克-Samuel-Belanik\" class=\"headerlink\" title=\"萨穆埃尔·贝拉尼克 Samuel Belaník\"></a>萨穆埃尔·贝拉尼克 Samuel Belaník</h3><p>俱乐部：日利纳B（斯甲）</p>\n<p><a href=\"https://www.transfermarkt.us/samuel-belanik/profil/spieler/800598\">Transfermarkt</a></p>\n<p>贝拉尼克正是得益于从U19到成年联赛的过渡期能够稳定地打上比赛，才能在欧青赛周期之后获得U20国家队的注意。他是日利纳B队的头号门将，与该队之前的不少门将类似，由于球队防守不佳，他也经常受到严酷的考验，并且在赛季初球队的震荡期拿出不错的发挥。</p>\n<p>轶闻：贝拉尼克还有另一个身份：他的爸爸卡罗尔·贝拉尼克是足协执委会副主席兼任日利纳队体育总监，因此一直有人认为他是“关系户”。</p>\n<h2 id=\"边后卫\"><a href=\"#边后卫\" class=\"headerlink\" title=\"边后卫\"></a>边后卫</h2><h3 id=\"萨穆埃尔·科帕塞克-Samuel-Kopasek\"><a href=\"#萨穆埃尔·科帕塞克-Samuel-Kopasek\" class=\"headerlink\" title=\"萨穆埃尔·科帕塞克 Samuel Kopásek\"></a>萨穆埃尔·科帕塞克 Samuel Kopásek</h3><p><a href=\"https://www.transfermarkt.us/samuel-kopasek/profil/spieler/583755\">Transfermarkt</a></p>\n<p>俱乐部：日利纳/日利纳B（斯甲）</p>\n<p>自从欧青赛备战期第一次注意到他的表现，笔者就一直在关注小个子科帕塞克。可以说他是斯洛伐克近年来最重要的边后卫新秀。科帕塞克身材不高，身体素质不错，踢法具侵略性，会在边路上下往返。他与卡普拉利克的配合是日利纳对阵国际米兰和萨尔茨堡青年队时的亮点。然而U20国家队缺少强力边锋，所以科帕塞克自己就成了进攻的发起。而且由于能力在众多边后卫中也是最强的，他还时不时要客串左路，但也有一些亮眼的发挥。帮助斯洛伐克杀进世青赛的进球就是他打进的。他的进攻路子主要还是自己靠爆发力突破，以及之后配合边锋打一些直塞，或者自己在无球情况下肋部插上，本身很少传中。</p>\n<p>去年欧青赛前科帕塞克就获得了一些成年队比赛的机会，但是因为身板问题在防守上经常吃亏。这赛季他更多地在B队踢斯甲，主要还是锻炼自己的进攻能力。他甚至还在本赛季踢过三中卫居右的中卫。</p>\n<p>轶闻：科帕塞克生于一个体育家庭，爸爸妈妈分别是足球和手球运动员。</p>\n<h3 id=\"尼科拉斯·希库拉-Nicolas-Sikula\"><a href=\"#尼科拉斯·希库拉-Nicolas-Sikula\" class=\"headerlink\" title=\"尼科拉斯·希库拉 Nicolas Šikula\"></a>尼科拉斯·希库拉 Nicolas Šikula</h3><p><a href=\"https://sportnet.sme.sk/futbalnet/clen/1268260/?page=1&q=Nicolas%20%C5%A0ikula\">斯洛伐克足协数据库页面</a></p>\n<p>俱乐部：波德布雷佐瓦（斯超）/卡琳诺沃矿工（斯乙）</p>\n<p>一位后防多面手，同样是左右边后卫都可以踢，但主要在国青队客串左边后卫。笔者其实不太认可他的实力，但是他也属于在从U19到成年队过渡中比赛时间比较有保障的，所以入选最终名单的可能性很高。另外他也在三中卫体系中踢过边中卫。</p>\n<p>轶闻：欧青赛之前，曾经有一位土耳其球迷在推特上杜撰了一则转会传闻，称来自多特蒙德和萨尔茨堡的球探在观察希库拉，但贝西克塔斯将捷足先登。笔者为此还专门找这位土耳其球迷核实，最终证明消息是编造的。</p>\n<h3 id=\"西蒙·米楚达-Simon-Micuda\"><a href=\"#西蒙·米楚达-Simon-Micuda\" class=\"headerlink\" title=\"西蒙·米楚达 Šimon Mičuda\"></a>西蒙·米楚达 Šimon Mičuda</h3><p><a href=\"https://sportnet.sme.sk/futbalnet/clen/1278959/?page=1&q=Simon%20Micuda\">斯洛伐克足协数据库页面</a></p>\n<p>俱乐部：特伦钦/特伦钦U19</p>\n<p>米楚达在去年乘着特伦钦U19夺冠的东风跳级进入U19国家队，而且在欧青赛上逐渐获得主力位置。他不像科帕塞克那样充满主动的侵略性攻，风格上有点像半中卫，防守时会主动向边路内收。</p>\n<p>欧青赛后米楚达成了特伦钦的重点栽培对象，甚至在卡尔佐纳就任国家队主教练后多次（有争议地）入选国家队候补名单。但是随着球队逐渐陷入保级的泥潭，米楚达回到了特伦钦队U19梯队，帮助球队争取联赛卫冕。</p>\n<p>轶闻：本赛季后半段，米楚达就失去了特伦钦一线队的首发位置，但依旧常常出现在大名单。有资深斯超媒体人透露，今年3月份丹麦超中日德兰的球探曾亲临现场考察米楚达，结果米楚达没有出场。</p>\n<h2 id=\"中卫\"><a href=\"#中卫\" class=\"headerlink\" title=\"中卫\"></a>中卫</h2><h3 id=\"塞巴斯蒂安·科沙-Sebastian-Kosa\"><a href=\"#塞巴斯蒂安·科沙-Sebastian-Kosa\" class=\"headerlink\" title=\"塞巴斯蒂安·科沙 Sebastián Kóša\"></a>塞巴斯蒂安·科沙 Sebastián Kóša</h3><p><a href=\"https://www.transfermarkt.us/sebastian-kosa/profil/spieler/582429\">Transfermarkt</a></p>\n<p>俱乐部：特尔纳瓦斯巴达克（斯超）</p>\n<p>自从两个赛季以前成为斯超的轮换主力，科沙就是斯洛伐克00后中卫中最好的苗子。他之前以已经连跳两级进入2000年龄段的U21国家队。</p>\n<p>科沙最早出任后腰，加盟特尔纳瓦斯巴达克之后改踢中卫，之后进步迅速。他个子不是很高，相对机动。虽然也有所谓“现代中卫”的影子，但比起联赛中诸多东施效颦的“现代中卫”，他的对抗稳健许多，阅读比赛的视野不错，而且能的外扩防守。他的空战能力得到了欧足联技术报告的认可，上赛季跟什科特尔搭档也对他的成长有很多帮助。面对传统中锋，特别是中锋背身拿球，科沙还是有一些吃力。不过在斯超的环境中这种前锋相对较少。</p>\n<p><img src=\"https://mediamanager.sportnet.online/images/1000x0xresize/pages/f/futbalsfz.sk/2021/11/snimka-obrazovky-2021-11-13-o-0-35-14-1.png\" alt=\"科沙在斯洛伐克U21国家队\"><span class=\"image-caption\">科沙在斯洛伐克U21国家队</span></p>\n<p>严格来说，随着他的第三个斯超赛季到来，科沙的成长已经逐渐放慢了。因此世青赛以及2025年的欧青赛对他来说是他一次绝好的更上一层楼的机会。</p>\n<p>轶闻：曾有记者问科沙在随队前往客场的长途飞行中会做些什么。科沙的答案是看书，而且号称看的是《时间简史》。</p>\n<h3 id=\"雅库布·卢卡-Jakub-Luka\"><a href=\"#雅库布·卢卡-Jakub-Luka\" class=\"headerlink\" title=\"雅库布·卢卡 Jakub Luka\"></a>雅库布·卢卡 Jakub Luka</h3><p><a href=\"https://www.transfermarkt.us/jakub-luka/profil/spieler/582389\">Transfermarkt</a></p>\n<p>俱乐部：下库宾</p>\n<p><img src=\"https://i.im.ge/2022/01/10/X2rcbD.jpg\" alt=\"卢卡\"><span class=\"image-caption\">卢卡</span></p>\n<p>卢卡原本是这一年龄段的稳定主力中卫，但是欧青赛上的他的表现让人失望。这虽然不一定能撼动他在大名单中的地位，但很可能会让他丢掉主力中卫的位置。归根结底就是卢卡这个身材瘦高的后卫绝对速度和反应偏慢，对抗又不够硬朗，造成他无论是踢上抢中卫和拖后中卫都存在重大隐患。不过有一位空战不错的高大中卫在特定情况下仍然是有作用的。</p>\n<h3 id=\"马雷克·乌伊拉基-Marek-Ujlaky\"><a href=\"#马雷克·乌伊拉基-Marek-Ujlaky\" class=\"headerlink\" title=\"马雷克·乌伊拉基 Marek Ujlaky\"></a>马雷克·乌伊拉基 Marek Ujlaky</h3><p><a href=\"https://sportnet.sme.sk/futbalnet/clen/1269362/\">斯洛伐克足协数据库页面</a></p>\n<p>俱乐部：特尔纳瓦斯巴达克（斯超）/马尔热尼采（斯乙）</p>\n<p>有人失意就有人得意。前面的卢卡在欧青赛上失意，而乌伊拉基就是中卫位置上的得意人物。乌伊拉基欧青赛之前的2021年3月才第一次参加集训，但之后就展现出弥补卢卡技术缺陷的能力。以至于在欧青赛上获得首发机会，并且是少数在欧青赛上发挥超出预期的斯洛伐克球员。乌伊拉基是个轻型中卫，上抢能力不错，同时也有一定的出球，跟科沙搭档显得更稳健。</p>\n<p>轶闻：他的爸爸（同样也叫马雷克）是特尔纳瓦斯巴达克的名宿，因此小乌伊拉基其实早就名声在外。</p>\n<h3 id=\"萨穆埃尔·巴金-Samuel-Bagin\"><a href=\"#萨穆埃尔·巴金-Samuel-Bagin\" class=\"headerlink\" title=\"萨穆埃尔·巴金 Samuel Bagín\"></a>萨穆埃尔·巴金 Samuel Bagín</h3><p><a href=\"https://www.transfermarkt.us/samuel-bagin/profil/spieler/726671\">transfermarkt</a></p>\n<p>巴金原本就是2004年龄段斯洛伐克国青队的主力中卫，上赛季也是帮助特伦钦U19夺得联赛冠军的功臣，但是去年秋天他遭遇重伤，缺席了7-12月的所有比赛。不过冬歇期后巴金彻底康复，并且一跃成为特伦钦的斯超主力中卫，也顺利回到了2004年龄段的U19国家队。</p>\n<p>巴金的风格跟卢卡其实类似，速度也不是很快。不过他的身材更壮实，不像卢卡那么瘦干。</p>\n<p>轶闻：这个名字怎么翻译我其实是有一点纠结，但是这确实是最接近原音的翻译了。</p>\n<h2 id=\"中场\"><a href=\"#中场\" class=\"headerlink\" title=\"中场\"></a>中场</h2><h3 id=\"多米尼克·霍利-Dominik-Holly\"><a href=\"#多米尼克·霍利-Dominik-Holly\" class=\"headerlink\" title=\"多米尼克·霍利 Dominik Hollý\"></a>多米尼克·霍利 Dominik Hollý</h3><p><a href=\"https://www.transfermarkt.us/dominik-holly/profil/spieler/802836\">Transfermarkt</a></p>\n<p>俱乐部：特伦钦（斯超）</p>\n<p>霍利是一位B2B中场，长期在这个年龄段的斯洛伐克国青队担任主力。他喜欢在右侧上下往返，甚至在进攻中去禁区争顶。他在欧青赛上展现出激昂的斗志，屡屡用肉搏为球队争下球权，以至于欧青赛之后不得不养伤一个半月，还差点造成特伦钦俱乐部和国家队的矛盾。虽然他不是球队的明星球员，却是球队坚韧精神的象征，也是斯洛伐克00后中后场球员中少数不惧怕对抗的。</p>\n<p>由于过去有踢前腰的经历，霍利也有一定的脚下技术。他在去年11月对阵沙特的热身赛中还有一次漂亮过人后的右脚远射破门。</p>\n<h3 id=\"阿图尔·加伊多什-Artur-Gajdos\"><a href=\"#阿图尔·加伊多什-Artur-Gajdos\" class=\"headerlink\" title=\"阿图尔·加伊多什 Artur Gajdoš\"></a>阿图尔·加伊多什 Artur Gajdoš</h3><p><a href=\"https://www.transfermarkt.us/artur-gajdos/profil/spieler/641657\">Transfermarkt</a></p>\n<p>俱乐部：特伦钦（斯超）</p>\n<p>加伊多什在2021年10月的三场热身赛中展现出来不错的盘带和传球思路，因此被球迷寄予厚望。然而他本身的角色介于10号位前腰和8号位中场之间，而且对进攻方向和节奏的掌控尚不成熟，所以在欧青赛上成了表现让人失望的球员之一，之后还丢掉了首发的位置。他的风格可能过于传统，跑动偏少，因此在需要大量逼抢的时候，他的地位便不如萨乌尔。</p>\n<p>特伦钦也把加伊多什视为重点培养对象，本赛季坐稳斯超主力。他的运动战组织实际上还是有待加强，但是射门和主罚定位球的质量颇高。他在斯超的5个助攻有4个来自定位球传中。欧青赛击败罗马尼亚的进球，也是源自他在右路主罚的任意球传中。</p>\n<p><img src=\"https://i.im.ge/2022/01/10/X2rYXM.jpg\" alt=\"加伊多什\"><span class=\"image-caption\">加伊多什</span></p>\n<h3 id=\"马里奥·萨乌尔-Mario-Sauer\"><a href=\"#马里奥·萨乌尔-Mario-Sauer\" class=\"headerlink\" title=\"马里奥·萨乌尔 Mário Sauer\"></a>马里奥·萨乌尔 Mário Sauer</h3><p><a href=\"https://www.transfermarkt.us/mario-sauer/profil/spieler/710885\">Transfermarkt</a></p>\n<p>俱乐部：日利纳（斯超）/日利纳B（斯甲）</p>\n<p>大萨乌尔因为在青年欧冠对国际米兰独中两元而一战成名。他和加伊多什也是典型的斯洛伐克当代攻击型中场的写照：瘦弱的小个子，动作速率不错，走后上得分路线。</p>\n<p>尽管是2004年龄段的球员，但本赛季萨乌尔彻底告别了U19联赛。实际上他在日利纳的踢法也不像前腰，而是中场几个执行跑动传切、后上得分和高位逼抢的工具人中场之一。他在欧青赛上的表现大概符合我的期待，因为我对这样的工兵中场期待也不高。</p>\n<p>轶闻：马里奥有一个小他一岁的弟弟莱奥，目前效力于费耶诺德青年队，是一个边置的技术型中场。严格地说，笔者更喜欢他弟弟那种球风：对进攻方向有更清晰把握，在边路拿球时也有多样的策略。大小萨乌尔都是日利纳从布拉迪斯拉发斯拉夫人的青年队挖角，因此也成了斯洛伐克国内球迷在攻击斯拉夫人队时常用的论据。</p>\n<h3 id=\"多米尼克·施奈德-Dominik-Snajder\"><a href=\"#多米尼克·施奈德-Dominik-Snajder\" class=\"headerlink\" title=\"多米尼克·施奈德 Dominik Šnajder\"></a>多米尼克·施奈德 Dominik Šnajder</h3><p><a href=\"https://www.transfermarkt.us/dominik-snajder/profil/spieler/582407\">Transfermarkt</a></p>\n<p>俱乐部：日利纳B</p>\n<p>如果不是日利纳U19去年在青年欧冠上的成功，施奈德很可能无缘欧青赛。因为他的身材比加伊多什和大萨乌尔还瘦、矮一些。欧青赛备战期间他展示出了一些突破的能力，所以入选了大名单，但是只踢了45分钟，有一些拉边回防的镜头。</p>\n<p>不过随着斯洛伐克U20开始与欧洲之外的对手热身，以及他本人进入成年队成为斯甲联赛的主力，他也展现出来一些不一样的东西，比如他的突破能力可以让他在面对沙特这样的弱旅时摇身一变成为一个类似洛博特卡的角色。但在硬仗中，这样的小个子中场太容易被掐死，因此他如果真的担任拖后组织者，会是一个非常冒险的举措。</p>\n<h3 id=\"马丁·奥拉维茨-Martin-Oravec\"><a href=\"#马丁·奥拉维茨-Martin-Oravec\" class=\"headerlink\" title=\"马丁·奥拉维茨 Martin Oravec\"></a>马丁·奥拉维茨 Martin Oravec</h3><p><a href=\"https://sportnet.sme.sk/futbalnet/clen/1329112/?page=1&q=Martin%20oravec\">斯洛伐克足协数据库页面</a></p>\n<p>俱乐部：日利纳B</p>\n<p>原本笔者认为他是日利纳青年欧冠中入选最没道理的一位，但是奥拉维茨在欧青赛正赛上实现了逆袭，证明外界对他的怀疑都是错的。因为他是斯洛伐克的中场中，最适合三中场居中拖后的，而且是在欧足联技术报告中，他的阅读比赛和夺回球权能力被特别指出。除了协助中后场出球梳理，他的防守站位也不错。他顶替哈拉布林上场之后，斯洛伐克的中后场稳健了许多。</p>\n<p>然而今年3月他因为伤病错过了U20国家队的集训，而且至今依旧伤缺，因此他的身体状况成疑。</p>\n<h3 id=\"马泰·索尔戈伊-Mate-Szolgai\"><a href=\"#马泰·索尔戈伊-Mate-Szolgai\" class=\"headerlink\" title=\"马泰·索尔戈伊 Máté Szolgai\"></a>马泰·索尔戈伊 Máté Szolgai</h3><p>俱乐部：沙莫林（斯甲）</p>\n<p><a href=\"https://sportnet.sme.sk/futbalnet/clen/1324055/?page=1&q=Mate%20Szolgai\">斯洛伐克足协数据库页面</a></p>\n<p>索尔戈伊的风格跟之前提到的霍利有几分相似，也是一个大量跑动的B2B中场，不过技术不如霍利细。他入选欧青赛最终名单实际上有些让人意外，而且他在欧青赛正赛的45分钟也显得手足无措。</p>\n<p>不过欧青赛后他成为斯甲联赛的主力，状态和能力都有一定的提高。代表作是本赛季斯洛伐克杯四分之一决赛，他与其他几位沙莫林的年轻球员用大量的奔跑和逼抢让布拉迪斯拉发斯拉夫人队手足无措。</p>\n<h2 id=\"前锋\"><a href=\"#前锋\" class=\"headerlink\" title=\"前锋\"></a>前锋</h2><h3 id=\"蒂莫泰伊·亚姆博尔-Timotej-Jambor\"><a href=\"#蒂莫泰伊·亚姆博尔-Timotej-Jambor\" class=\"headerlink\" title=\"蒂莫泰伊·亚姆博尔 Timotej Jambor\"></a>蒂莫泰伊·亚姆博尔 Timotej Jambor</h3><p><a href=\"https://www.transfermarkt.us/timotej-jambor/profil/spieler/582384\">Transfermarkt</a></p>\n<p>俱乐部：日利纳（斯超）</p>\n<p>身为U20国家队的队长、不少人心目中斯洛伐克足球最具潜力的锋线新星，亚姆博尔的负担一定很重。他在俱乐部的角色逐渐成为游击型中锋，拿球做球乃至带球次数越来越少，实际上让一些人担心他接下来的发展。因为斯洛伐克过去几位这样的年轻前锋发展都不好。</p>\n<p>在欧青赛上，亚姆博尔也陷入迷茫之中，甚至只能从日利纳B队开始这个赛季。起初三轮没有进球还让更多的球迷对他产生怀疑，但随着在斯甲的一次大四喜，他众望所归回到一线队，之后打进8个斯超进球。但还是像之前讲的，他是一个无球前锋，虽然射术不错。</p>\n<p>为了配合他的技术特点，不管是俱乐部还是国家队，都在用传跑为亚姆博尔创造空间，不让他承担过多的拿球带球任务。这一点对队友的消耗其实不小。笔者其实对这一点不太满意。他与另一名中锋格里格尔在球队的作用虽然都很大，但是具体的贡献形式相差很多。</p>\n<p><img src=\"https://mediamanager.sportnet.online/images/670x0xresize/pages/f/futbalsfz.sk/2021/11/45-xt2s3854.jpg.webp\" alt=\"亚姆博尔佩戴U19国家队队长袖标\"><span class=\"image-caption\">亚姆博尔佩戴U19国家队队长袖标</span></p>\n<p>轶闻：亚姆博尔的爸爸米兰·亚姆博尔曾代表斯洛伐克的普霍夫队在2003年的欧洲联盟杯的比赛中<a href=\"https://www.transfermarkt.us/fk-puchov_fc-barcelona/index/spielbericht/73\">进球绝平巴塞罗那</a>。</p>\n<h3 id=\"亚当·格里格尔-Adam-Griger\"><a href=\"#亚当·格里格尔-Adam-Griger\" class=\"headerlink\" title=\"亚当·格里格尔 Adam Griger\"></a>亚当·格里格尔 Adam Griger</h3><p><a href=\"https://www.transfermarkt.us/adam-griger/profil/spieler/641676\">Transfermarkt</a></p>\n<p>俱乐部：卡利亚里U19</p>\n<p>格里格尔是近年来斯洛伐克年轻球员里少有的传统高中锋。与长年被誉为“锋线天才”的亚姆博尔不同，如果不是在2021年突然在斯超出场、随后前往奥地利发展，格里格尔很可能就会被埋没在斯洛伐克的青年联赛中。而他也抓住了机会，在欧青赛的大舞台上展现出传统中锋的价值。对阵罗马尼亚，他在亚姆博尔迷失之际替补登场，用背身拿球和拉边压制边后卫给队友创造空间，而且自己打进比赛唯一进球。在林茨的预备队降级后，他到意大利踢球也是个不错的选择，毕竟意大利仍然有不少传统中锋的生存空间。而在2004年龄段的U19国家队，格里格尔则是当仁不让的头号中锋。</p>\n<p>他的中锋特点很明显，背身拿球或者在进攻中拉边做球都可以。但是脚下技术和射门脚法都有一些粗糙，而且移动偏慢的确跟U20国家队整体的打法不太一致。欧青赛首战法国，老鲁斯纳克让他踢边锋，结果没有速度的格里格尔在防守回落到右边路之后也很吃力。</p>\n<p>轶闻：2022年11月，足协在一次采访中曾问到格里格尔是不是因为长相原因在卡利亚里青年队被队友成为“哈兰德”。这两人的风格显然迥异。当时时值U20国家队与日本、印度尼西亚和沙特热身，采访被印度尼西亚球迷发现之后大加嘲讽。结果印度尼西亚不仅那场比赛被逆转，还因为丢掉了U20世界杯的主办权而丧失参赛资格。</p>\n<h3 id=\"亚当·加希-Adam-Gazi\"><a href=\"#亚当·加希-Adam-Gazi\" class=\"headerlink\" title=\"亚当·加希 Adam Gaži\"></a>亚当·加希 Adam Gaži</h3><p><a href=\"https://www.transfermarkt.us/adam-gazi/profil/spieler/720769\">Transfermarkt</a></p>\n<p>俱乐部：利普托夫斯基米库拉什（斯超）</p>\n<p>以加希为代表的这三个边路攻击手，都不是2002年龄段的卡普拉利克那样拥有强大爆发力的边锋，没有办法靠速度强行超车。尤其是加希和斯利亚茨基，风格上更像是边置的有一定技术的攻击型中场，偏向于用脚下技术和节奏的变化突破，或者是配合边后卫和压上的中场打小组配合。</p>\n<p>加希本赛季在特伦钦面临外援阿赞哥和和同龄人德米特拉的双重竞争，所以选择租借到弱旅利普托夫斯基米库拉什。然而由于该队实力过弱，加希虽然有不错的出场时间，但是数据上和成长上都比较有限，表现不如2021-22赛季。</p>\n<p><img src=\"https://i.im.ge/2022/01/10/X2rjoy.jpg\" alt=\"加希\"><span class=\"image-caption\">加希</span></p>\n<p>轶闻：加希从10岁起就效力于特伦钦，但本赛季他选择租借加盟斯超的垫底球队，而且在特伦钦的主力右边锋受伤后也没有驰援母队的意愿。有人认为这揭示了特伦钦俱乐部的糟糕管理水准，以及球员与球队之间的隔阂。</p>\n<h3 id=\"维克托·斯利亚茨基-Viktor-Sliacky\"><a href=\"#维克托·斯利亚茨基-Viktor-Sliacky\" class=\"headerlink\" title=\"维克托·斯利亚茨基 Viktor Sliacky\"></a>维克托·斯利亚茨基 Viktor Sliacky</h3><p><a href=\"https://www.transfermarkt.us/viktor-sliacky/profil/spieler/802867\">Transfermarkt</a></p>\n<p>俱乐部：彼得扎尔卡（斯甲）</p>\n<p>矮个子斯利亚茨基的位置介乎前腰和左边锋之间，可能更接近左边锋。欧青赛备战阶段他还显得太过瘦小，不过过去的一个赛季，由于能够在斯甲踢上轮换主力，他有不小的进步，身板看上去也更硬了。他和科帕塞克在热身赛中曾经在左路打出过不错的配合（科帕塞克强突和直塞与斯利亚茨基的斜插、内切配合），也许可以在世青赛上复现。</p>\n<p>轶闻：斯利亚茨基是大名单中唯一一位没有在斯超俱乐部及其效力过的球员。他和乔卡的斯超经验都为0，但乔卡的所有权仍属于斯超球队多瑙斯特雷达。</p>\n<h3 id=\"巴林特·乔卡-Balint-Csoka\"><a href=\"#巴林特·乔卡-Balint-Csoka\" class=\"headerlink\" title=\"巴林特·乔卡 Bálint Csóka\"></a>巴林特·乔卡 Bálint Csóka</h3><p><a href=\"https://www.transfermarkt.us/balint-csoka/profil/spieler/809945\">Transfermarkt</a></p>\n<p>俱乐部：沙莫林（斯甲）</p>\n<p>乔卡是世青赛大名单中唯一一位在欧青赛周期没有任何U19国青队经验的球员。这也可以理解，因为当时他还在多瑙斯特雷达的U19梯队摸爬滚打。但欧青赛之后他在沙莫林发挥不错，特别是8月份在联赛连续三轮进球，让他敲开了U20国家队的大门。</p>\n<p>比起加希和斯利亚茨基，乔卡的身材比较高大，进攻特点可能更加直接，脚下技术也不如加、斯二人细，但无球跑动颇有想法。并且乔卡左右路踢得都比较自然，比起加希鲜明的右边锋和斯利亚茨基鲜明的左路球员特点，在位置上显得比较灵活。</p>\n<h2 id=\"球队阵容浅析\"><a href=\"#球队阵容浅析\" class=\"headerlink\" title=\"球队阵容浅析\"></a>球队阵容浅析</h2><p>U19国家队去年10月击败荷兰和葡萄牙、9月逼平法国，以及日利纳U19在青年欧冠淘汰国际米兰、险些淘汰萨尔茨堡的例子，是上述战术思路的最佳成果。这次在小组赛再次对上法国和意大利，也许球队上下会有一定的底气。然而比赛样本的数量不多，而且对手的重视程度也会不一样。在与实力接近的球队（捷克、匈牙利、北马其顿、挪威）的比赛中，这支斯洛伐克U19未尝胜绩。在阵地战中，身体对抗和速度的劣势使得斯洛伐克U19在攻防两端都处于下风，这也是相当需要担心的一点。</p>\n<p>不算守门员，从右到左，斯洛伐克U19最有可能的阵容是这样的：科帕塞克，科沙，卢卡，希库拉 - 霍利，哈拉布林，加伊多什 - 加希，亚姆博尔，米绍维奇。可以看做右攻左守，但考虑到球队前场对抗能力不强，中场又都是小个子，实际上应该还是靠中后场堆人挨打，然后用前场的速度型球员逼抢或者中后场断球后的长传制造反击。</p>\n<p>阵地战也绝非这支球队所长。笔者认为寻求亚姆博尔和格里格尔共存的方案至关重要，因为高中锋格里格尔的对抗和做球能力与亚姆博尔的速度和抢点嗅觉互补，不应该被忽视。当然，这两人都不是纯粹的边路球员，这也意味着两人同时在场时，要么有一人照顾边路，要么切换到类似4312的无边锋阵型。这样的安排也能多少减缓霍利、哈拉布林、加伊多什这三个个子相对矮的中场的防守压力（后两位只有一米七身高，而且除非把科沙推向中场，替补席上也没有中场防守比较强的点）。这需要球队在备战期仔细打磨。</p>\n<p>最糟糕的情况就是主教练鲁斯纳克再次寻求三中卫。首先是因为这支U19组队以来，摆出三中卫的比赛效果不会（1-6德国，0-3匈牙利），而且原本助攻能力不错的边后卫也因为边锋、前锋对抗的弱势而被压制（1-0埃及U20）。其次是鲁斯纳克不愿意用速度较快的中卫在三中卫中靠边，海奇科速度勉强可以，但对抗不足；拿高而慢的卢卡打这个位置则屡次被爆。从训练营的两场热身赛的阵容来看，鲁斯纳克还是在往433和防守反击上靠。</p>\n<p>乘着主办这届欧青赛的东风，斯洛伐克球员幸运地获得了与欧洲同年龄段最高水平球员过招的机会。笔者对他们没什么成绩上期待，关键要看他们跟欧洲最高水平差距到底有多大，斯超斯甲联赛的年轻化到底是卓有成效，还是数量胜过质量，抑或是某些球队关起门来自我陶醉。当然，如果能有机会去拼U20世界杯的参赛资格，就更好了。</p>\n","text":"2023年世青赛其他专题：前瞻 2022年欧青赛专题：球员简介及前瞻、比赛赛况 最后更新： 2022年4月30日本文写于斯洛伐克队大名单公布之前，所列球员是否能够入选纯属猜测。大名单正式公布后将会进行补充，敬请期待！ 前言每次介绍斯洛伐克的年轻球员，我的心里都是矛盾的。因为一个青...","link":"","photos":[],"count_time":{"symbolsCount":"9.1k","symbolsTime":"8 mins."},"categories":[{"name":"斯洛伐克国家队","slug":"斯洛伐克国家队","count":40,"path":"api/categories/斯洛伐克国家队.json"}],"tags":[{"name":"2023","slug":"2023","count":17,"path":"api/tags/2023.json"},{"name":"前瞻总结","slug":"前瞻总结","count":8,"path":"api/tags/前瞻总结.json"},{"name":"2023年世青赛","slug":"2023年世青赛","count":2,"path":"api/tags/2023年世青赛.json"}],"toc":"<ol class=\"toc\"><li class=\"toc-item toc-level-2\"><a class=\"toc-link\" href=\"#%E5%89%8D%E8%A8%80\"><span class=\"toc-text\">前言</span></a></li><li class=\"toc-item toc-level-2\"><a class=\"toc-link\" href=\"#%E5%A4%A7%E5%90%8D%E5%8D%95%E4%BB%8B%E7%BB%8D\"><span class=\"toc-text\">大名单介绍</span></a><ol class=\"toc-child\"><li class=\"toc-item toc-level-3\"><a class=\"toc-link\" href=\"#%E9%97%A8%E5%B0%86\"><span class=\"toc-text\">门将</span></a><ol class=\"toc-child\"><li class=\"toc-item toc-level-4\"><a class=\"toc-link\" href=\"#%E8%8F%B2%E5%88%A9%E6%99%AE%C2%B7%E5%B7%B4%E6%8B%89%E6%97%A5-Filip-Balaz\"><span class=\"toc-text\">菲利普·巴拉日 Filip Baláž</span></a></li><li class=\"toc-item toc-level-4\"><a class=\"toc-link\" href=\"#%E4%BA%9A%E5%BD%93%C2%B7%E8%B5%AB%E5%B0%94%E5%AD%A3%E7%BA%B3-Adam-Hrdina\"><span class=\"toc-text\">亚当·赫尔季纳 Adam Hrdina</span></a></li></ol></li><li class=\"toc-item toc-level-3\"><a class=\"toc-link\" href=\"#%E8%90%A8%E7%A9%86%E5%9F%83%E5%B0%94%C2%B7%E8%B4%9D%E6%8B%89%E5%B0%BC%E5%85%8B-Samuel-Belanik\"><span class=\"toc-text\">萨穆埃尔·贝拉尼克 Samuel Belaník</span></a></li></ol></li><li class=\"toc-item toc-level-2\"><a class=\"toc-link\" href=\"#%E8%BE%B9%E5%90%8E%E5%8D%AB\"><span class=\"toc-text\">边后卫</span></a><ol class=\"toc-child\"><li class=\"toc-item toc-level-3\"><a class=\"toc-link\" href=\"#%E8%90%A8%E7%A9%86%E5%9F%83%E5%B0%94%C2%B7%E7%A7%91%E5%B8%95%E5%A1%9E%E5%85%8B-Samuel-Kopasek\"><span class=\"toc-text\">萨穆埃尔·科帕塞克 Samuel Kopásek</span></a></li><li class=\"toc-item toc-level-3\"><a class=\"toc-link\" href=\"#%E5%B0%BC%E7%A7%91%E6%8B%89%E6%96%AF%C2%B7%E5%B8%8C%E5%BA%93%E6%8B%89-Nicolas-Sikula\"><span class=\"toc-text\">尼科拉斯·希库拉 Nicolas Šikula</span></a></li><li class=\"toc-item toc-level-3\"><a class=\"toc-link\" href=\"#%E8%A5%BF%E8%92%99%C2%B7%E7%B1%B3%E6%A5%9A%E8%BE%BE-Simon-Micuda\"><span class=\"toc-text\">西蒙·米楚达 Šimon Mičuda</span></a></li></ol></li><li class=\"toc-item toc-level-2\"><a class=\"toc-link\" href=\"#%E4%B8%AD%E5%8D%AB\"><span class=\"toc-text\">中卫</span></a><ol class=\"toc-child\"><li class=\"toc-item toc-level-3\"><a class=\"toc-link\" href=\"#%E5%A1%9E%E5%B7%B4%E6%96%AF%E8%92%82%E5%AE%89%C2%B7%E7%A7%91%E6%B2%99-Sebastian-Kosa\"><span class=\"toc-text\">塞巴斯蒂安·科沙 Sebastián Kóša</span></a></li><li class=\"toc-item toc-level-3\"><a class=\"toc-link\" href=\"#%E9%9B%85%E5%BA%93%E5%B8%83%C2%B7%E5%8D%A2%E5%8D%A1-Jakub-Luka\"><span class=\"toc-text\">雅库布·卢卡 Jakub Luka</span></a></li><li class=\"toc-item toc-level-3\"><a class=\"toc-link\" href=\"#%E9%A9%AC%E9%9B%B7%E5%85%8B%C2%B7%E4%B9%8C%E4%BC%8A%E6%8B%89%E5%9F%BA-Marek-Ujlaky\"><span class=\"toc-text\">马雷克·乌伊拉基 Marek Ujlaky</span></a></li><li class=\"toc-item toc-level-3\"><a class=\"toc-link\" href=\"#%E8%90%A8%E7%A9%86%E5%9F%83%E5%B0%94%C2%B7%E5%B7%B4%E9%87%91-Samuel-Bagin\"><span class=\"toc-text\">萨穆埃尔·巴金 Samuel Bagín</span></a></li></ol></li><li class=\"toc-item toc-level-2\"><a class=\"toc-link\" href=\"#%E4%B8%AD%E5%9C%BA\"><span class=\"toc-text\">中场</span></a><ol class=\"toc-child\"><li class=\"toc-item toc-level-3\"><a class=\"toc-link\" href=\"#%E5%A4%9A%E7%B1%B3%E5%B0%BC%E5%85%8B%C2%B7%E9%9C%8D%E5%88%A9-Dominik-Holly\"><span class=\"toc-text\">多米尼克·霍利 Dominik Hollý</span></a></li><li class=\"toc-item toc-level-3\"><a class=\"toc-link\" href=\"#%E9%98%BF%E5%9B%BE%E5%B0%94%C2%B7%E5%8A%A0%E4%BC%8A%E5%A4%9A%E4%BB%80-Artur-Gajdos\"><span class=\"toc-text\">阿图尔·加伊多什 Artur Gajdoš</span></a></li><li class=\"toc-item toc-level-3\"><a class=\"toc-link\" href=\"#%E9%A9%AC%E9%87%8C%E5%A5%A5%C2%B7%E8%90%A8%E4%B9%8C%E5%B0%94-Mario-Sauer\"><span class=\"toc-text\">马里奥·萨乌尔 Mário Sauer</span></a></li><li class=\"toc-item toc-level-3\"><a class=\"toc-link\" href=\"#%E5%A4%9A%E7%B1%B3%E5%B0%BC%E5%85%8B%C2%B7%E6%96%BD%E5%A5%88%E5%BE%B7-Dominik-Snajder\"><span class=\"toc-text\">多米尼克·施奈德 Dominik Šnajder</span></a></li><li class=\"toc-item toc-level-3\"><a class=\"toc-link\" href=\"#%E9%A9%AC%E4%B8%81%C2%B7%E5%A5%A5%E6%8B%89%E7%BB%B4%E8%8C%A8-Martin-Oravec\"><span class=\"toc-text\">马丁·奥拉维茨 Martin Oravec</span></a></li><li class=\"toc-item toc-level-3\"><a class=\"toc-link\" href=\"#%E9%A9%AC%E6%B3%B0%C2%B7%E7%B4%A2%E5%B0%94%E6%88%88%E4%BC%8A-Mate-Szolgai\"><span class=\"toc-text\">马泰·索尔戈伊 Máté Szolgai</span></a></li></ol></li><li class=\"toc-item toc-level-2\"><a class=\"toc-link\" href=\"#%E5%89%8D%E9%94%8B\"><span class=\"toc-text\">前锋</span></a><ol class=\"toc-child\"><li class=\"toc-item toc-level-3\"><a class=\"toc-link\" href=\"#%E8%92%82%E8%8E%AB%E6%B3%B0%E4%BC%8A%C2%B7%E4%BA%9A%E5%A7%86%E5%8D%9A%E5%B0%94-Timotej-Jambor\"><span class=\"toc-text\">蒂莫泰伊·亚姆博尔 Timotej Jambor</span></a></li><li class=\"toc-item toc-level-3\"><a class=\"toc-link\" href=\"#%E4%BA%9A%E5%BD%93%C2%B7%E6%A0%BC%E9%87%8C%E6%A0%BC%E5%B0%94-Adam-Griger\"><span class=\"toc-text\">亚当·格里格尔 Adam Griger</span></a></li><li class=\"toc-item toc-level-3\"><a class=\"toc-link\" href=\"#%E4%BA%9A%E5%BD%93%C2%B7%E5%8A%A0%E5%B8%8C-Adam-Gazi\"><span class=\"toc-text\">亚当·加希 Adam Gaži</span></a></li><li class=\"toc-item toc-level-3\"><a class=\"toc-link\" href=\"#%E7%BB%B4%E5%85%8B%E6%89%98%C2%B7%E6%96%AF%E5%88%A9%E4%BA%9A%E8%8C%A8%E5%9F%BA-Viktor-Sliacky\"><span class=\"toc-text\">维克托·斯利亚茨基 Viktor Sliacky</span></a></li><li class=\"toc-item toc-level-3\"><a class=\"toc-link\" href=\"#%E5%B7%B4%E6%9E%97%E7%89%B9%C2%B7%E4%B9%94%E5%8D%A1-Balint-Csoka\"><span class=\"toc-text\">巴林特·乔卡 Bálint Csóka</span></a></li></ol></li><li class=\"toc-item toc-level-2\"><a class=\"toc-link\" href=\"#%E7%90%83%E9%98%9F%E9%98%B5%E5%AE%B9%E6%B5%85%E6%9E%90\"><span class=\"toc-text\">球队阵容浅析</span></a></li></ol>","author":{"name":"斯洛伐克足球狂做梦","slug":"blog-author","avatar":"/Images/icon.PNG","link":"https://svkfootballdream.github.io/","description":"中文斯洛伐克足球信息站","socials":{"github":"","twitter":"","stackoverflow":"","wechat":"","qq":"","weibo":"","zhihu":"","csdn":"","juejin":"","customs":{}}},"mapped":true,"prev_post":{"title":"2022-05-03：斯洛伐克足球简讯","uid":"bb7cf7743e7d716e168fc98839d9c433","slug":"2022-05-03-digest","date":"2022-05-03T01:21:23.000Z","updated":"2022-05-03T05:12:37.957Z","comments":true,"path":"api/articles/2022-05-03-digest.json","keywords":null,"cover":"https://i.imgur.com/zfOyLG3.jpg","text":"祝各位读者劳动节快乐、五一长假快乐！ 苦心人天不负，哈姆西克终获联赛冠军哈姆西克在斯洛伐克国家队已经创造了一项又一项纪录（出场次数、进球数、欧洲杯出场数、斯洛伐克足球先生次数……），也是那不勒斯俱乐部的传奇人物，但可惜的是他的职业生涯中还从未获得过联赛冠军，甚至在斯洛伐克联赛踢球...","link":"","photos":[],"count_time":{"symbolsCount":"2.7k","symbolsTime":"2 mins."},"categories":[{"name":"简讯","slug":"简讯","count":88,"path":"api/categories/简讯.json"}],"tags":[{"name":"2022","slug":"2022","count":45,"path":"api/tags/2022.json"}],"author":{"name":"斯洛伐克足球狂做梦","slug":"blog-author","avatar":"/Images/icon.PNG","link":"https://svkfootballdream.github.io/","description":"中文斯洛伐克足球信息站","socials":{"github":"","twitter":"","stackoverflow":"","wechat":"","qq":"","weibo":"","zhihu":"","csdn":"","juejin":"","customs":{}}}},"next_post":{"title":"2022-04-26：斯洛伐克足球简讯","uid":"8615338c1acaeeec2b2081512e45ffed","slug":"2022-04-26-digest","date":"2022-04-25T01:30:29.000Z","updated":"2022-04-27T01:33:32.171Z","comments":true,"path":"api/articles/2022-04-26-digest.json","keywords":null,"cover":null,"text":"斯洛伐克U19国家队首期欧青赛集训名单距离在斯洛伐克本土进行的U19欧青赛已经不到两个月了。斯洛伐克U19国家队主教练老鲁斯纳克在上周三（20日）公布了欧青赛备战的第一份集训名单。球队在上周末集结，并与斯甲的沙莫林进行了一场闭门热身赛，球队1-4落败。原本球队可以与匈牙利U19热...","link":"","photos":[],"count_time":{"symbolsCount":"4k","symbolsTime":"4 mins."},"categories":[{"name":"简讯","slug":"简讯","count":88,"path":"api/categories/简讯.json"}],"tags":[{"name":"2022","slug":"2022","count":45,"path":"api/tags/2022.json"}],"author":{"name":"斯洛伐克足球狂做梦","slug":"blog-author","avatar":"/Images/icon.PNG","link":"https://svkfootballdream.github.io/","description":"中文斯洛伐克足球信息站","socials":{"github":"","twitter":"","stackoverflow":"","wechat":"","qq":"","weibo":"","zhihu":"","csdn":"","juejin":"","customs":{}}}}}