{"title":"2023年夏季休赛期斯洛伐克足球简讯汇总（持续更新）","uid":"9fcd568f4016d1c7b3720c2fdd4b3cba","slug":"2023-summer-update","date":"2023-05-29T04:09:54.000Z","updated":"2023-06-09T12:50:07.017Z","comments":true,"path":"api/articles/2023-summer-update.json","keywords":null,"cover":[],"content":"<blockquote><span class=\"custom-blockquote-svg\"><svg width=\"24\" height=\"24\" viewBox=\"0 0 24 24\" fill=\"\" xmlns=\"http://www.w3.org/2000/svg\" data-reactroot=\"\">\n<path fill=\"\" d=\"M22 12C22 6.5 17.5 2 12 2C6.5 2 2 6.5 2 12C2 17.5 6.5 22 12 22C13.8 22 15.5 21.5 17 20.6L22 22L20.7 17C21.5 15.5 22 13.8 22 12Z\" undefined=\"1\"></path>\n<path fill=\"\" d=\"M15.97 11.5H16.04C17.12 11.5 18 12.38 18 13.47V13.53C18 14.62 17.12 15.5 16.03 15.5H15.96C14.88 15.5 14 14.62 14 13.53V13.46C14 12.38 14.88 11.5 15.97 11.5Z\" undefined=\"1\"></path>\n<path fill=\"\" d=\"M7.97 11.5H8.04C9.12 11.5 10 12.38 10 13.47V13.53C10 14.62 9.12 15.5 8.03 15.5H7.97C6.88 15.5 6 14.62 6 13.53V13.46C6 12.38 6.88 11.5 7.97 11.5Z\" undefined=\"1\"></path>\n<path stroke-linejoin=\"round\" stroke-linecap=\"round\" stroke-miterlimit=\"10\" stroke-width=\"2\" stroke=\"\" d=\"M17 8.5C15.23 8.97 14.07 10.84 14.01 13.27C14 13.33 14 13.4 14 13.47V13.5\"></path>\n<path stroke-linejoin=\"round\" stroke-linecap=\"round\" stroke-miterlimit=\"10\" stroke-width=\"2\" stroke=\"\" d=\"M9 8.5C7.23 8.97 6.07 10.84 6.01 13.27C6 13.33 6 13.4 6 13.47V13.5\"></path>\n<path stroke-linejoin=\"round\" stroke-linecap=\"round\" stroke-miterlimit=\"10\" stroke-width=\"2\" stroke=\"\" d=\"M15.97 11.5H16.04C17.12 11.5 18 12.38 18 13.47V13.53C18 14.62 17.12 15.5 16.03 15.5H15.96C14.88 15.5 14 14.62 14 13.53V13.46C14 12.38 14.88 11.5 15.97 11.5Z\"></path>\n<path stroke-linejoin=\"round\" stroke-linecap=\"round\" stroke-miterlimit=\"10\" stroke-width=\"2\" stroke=\"\" d=\"M7.97 11.5H8.04C9.12 11.5 10 12.38 10 13.47V13.53C10 14.62 9.12 15.5 8.03 15.5H7.97C6.88 15.5 6 14.62 6 13.53V13.46C6 12.38 6.88 11.5 7.97 11.5Z\"></path>\n</svg>\n</span><p>最近更新：2023年6月1日。本文争取每日更新，直到新赛季俱乐部欧战开始回到周更。</p></blockquote>\n<p>2023年世青赛专题：<a href=\"/post/2023-u20-world-preview\">前瞻</a>、<a href=\"/post/2023-u20-world-players\">球员</a>、<a href=\"/post/2023-u20-world-updates\">动态更新</a>、<a href=\"/post/2023-u20-world-matches\">比赛赛况</a></p>\n<p>6月份国家队赛程（北京时间）见下<br>| 比赛时间 | 对手 |<br>|—|—|<br>| 6月6日23:00 | 捷克U18 |<br>| 6月9日17:00 | 捷克U18 |<br>| 6月15日23:30 | 匈牙利U21 |<br>| 6月18日02:45 | 冰岛（欧预赛） |<br>| 6月20日23:30 | 奥地利U21 |<br>| 6月21日02:45 | 列支敦士登（欧预赛）|</p>\n<h2 id=\"哈姆西克宣布退役\"><a href=\"#哈姆西克宣布退役\" class=\"headerlink\" title=\"哈姆西克宣布退役\"></a>哈姆西克宣布退役</h2><p>6月1日，哈姆西克在个人网站和社交平台上宣布，他将在本赛季结束后退役，结束自己传奇的球员生涯。他在6月3日的土超联赛中上演职业生涯的谢幕演出，取得一球一助攻。</p>\n<p><img src=\"https://i4.hurimg.com/i/hurriyet/75/750x422/647b74374e3fe108542ced01.jpg\" alt=\"哈姆西克在告别战中进球\"><span class=\"image-caption\">哈姆西克在告别战中进球</span></p>\n<p>6月7日星期三，哈姆西克来到国家队训练营报道。他一方面表示自己这次仍然是以普通球员身份前来，他从未想到还能回到国家队，一方面也表示了对卡尔佐纳的支持。他在记者会上同时也透露了自己的下一步：今年7月开始，他将在自己的哈姆西克足球学校担任U15梯队主教练，手下的球员包括自己的大儿子克里斯蒂安。</p>\n<h2 id=\"斯洛伐克各级国家队简讯\"><a href=\"#斯洛伐克各级国家队简讯\" class=\"headerlink\" title=\"斯洛伐克各级国家队简讯\"></a>斯洛伐克各级国家队简讯</h2><p>6月份的两场欧预赛、两场U21国家队比赛和两场U18国家队比赛信息详见本期的<a href=\"/post/2023-06-nt-digest\">国家队信息汇总</a>。</p>\n<ul>\n<li>6月9日：国家队大名单公布。</li>\n<li>6月6日：U21国家队名单公布，详见<a href=\"https://futbalsfz.sk/u21-trener-kentos-nominoval-na-junove-zapasy-23-hracov/\">足协新闻稿</a>。</li>\n<li>6月1日：国家队主帅卡尔佐纳公布了一份30人的训练营名单。</li>\n<li>5月31日：U20国家队在世青赛八分之一决赛1-5输给哥伦比亚，结束本次比赛征程。</li>\n<li>5月29日：U18国家队（2005年龄段）在6月6日和9日对阵捷克的比赛大名单公布，详见<a href=\"https://futbalsfz.sk/u18-nominacia-na-junovy-dvojzapas-s-ceskom/\">足协新闻稿</a>。</li>\n<li>5月28日：斯洛伐克U20国家队确定晋级世青赛16强，将在31日（北京时间6月1日凌晨01:30）对阵哥伦比亚。</li>\n</ul>\n<h2 id=\"斯洛伐克海外球员新闻\"><a href=\"#斯洛伐克海外球员新闻\" class=\"headerlink\" title=\"斯洛伐克海外球员新闻\"></a>斯洛伐克海外球员新闻</h2><ul>\n<li>6月5日：之前从布拉迪斯拉发斯拉夫人租借到比乙贝费伦队的右边后卫/右边前卫赫恩察尔被贝费伦队买断。赫恩察尔在贝费伦租借了半个赛季，表现出色。他与贝费伦正式签订两年的合约，并带有续约一年的选项。<a href=\"https://skbeveren.be/2023/06/verlenging-hrncar/\">俱乐部官网新闻</a></li>\n<li>5月30日：国脚施朗茨（Ivan Schranz）与布拉格斯拉维亚续约到2026年。</li>\n<li>5月26日：前锋图普塔（Ľubomír Tupta）被捷甲利贝雷茨队买断。之前他是从佩斯卡拉租借到利贝雷茨。<a href=\"https://www.fcslovanliberec.cz/clanek.asp?id=V-Liberci-se-citim-velmi-dobre-rika-spokojeny-Tupta-15139\">俱乐部官网新闻</a></li>\n</ul>\n<h2 id=\"斯洛伐克国内联赛新闻（球员）\"><a href=\"#斯洛伐克国内联赛新闻（球员）\" class=\"headerlink\" title=\"斯洛伐克国内联赛新闻（球员）\"></a>斯洛伐克国内联赛新闻（球员）</h2><ul>\n<li>6月8日：布拉迪斯拉发斯拉夫人免费签下奥地利前国脚中卫凯文·维默尔（Kevin Wimmer），合约为期三年。</li>\n<li>6月7日：斯超班斯卡-比斯特里察杜克拉的球员库普奇克、巴利奇（租借）、米哈尔·法什科离队。米哈洛夫采的黑山后卫采克利奇加盟波德戈里察未来。</li>\n<li>6月6日：斯超升班马科希策从布拉迪斯拉发斯拉夫人签下斯洛文尼亚前锋梅德维德。</li>\n<li>6月3日：斯超布拉迪斯拉发斯拉夫人从德比死敌特尔纳瓦斯巴达克免费签下希腊后腰萨维季斯。萨维季斯跟特尔纳瓦斯巴达克的合同已经到期，新合同为期三年。</li>\n<li>6月3日：斯超米哈洛夫采队的西班牙中场布里安·佩尼亚转会到拉脱维亚顶级联赛的里加FC。兹拉特莫拉夫采的本土中卫米哈尔·平特尔加盟北马其顿联赛的什库皮（FC Shkupi），该队是北马其顿顶级联赛亚军。</li>\n<li>6月1日：斯超特尔纳瓦斯巴达克签下刚刚合同期满离队的特伦钦中场巴伊诺维奇。</li>\n<li>5月31日：斯超多瑙斯特雷达队的波黑中卫默罕默德贝戈维奇离队，转会到奥林匹亚卢布尔雅那。</li>\n<li>5月29日：斯超鲁容贝罗克队宣布不与主教练斯特鲁哈尔续约，斯特鲁哈尔因此正式离任。</li>\n<li>5月29日：斯超特伦钦队宣布巴伊诺维奇、拉夫林契克、马杜、阿赞戈、久里什卡离队。其中阿赞戈确定加盟特尔纳瓦斯巴达克。</li>\n</ul>\n<h2 id=\"斯洛伐克国内联赛新闻（球队、教练）\"><a href=\"#斯洛伐克国内联赛新闻（球队、教练）\" class=\"headerlink\" title=\"斯洛伐克国内联赛新闻（球队、教练）\"></a>斯洛伐克国内联赛新闻（球队、教练）</h2><ul>\n<li>6月5日：斯超鲁容贝罗克队宣布，前任主帅斯特鲁哈尔的助理教练<strong>彼得·托姆科</strong>（Peter Tomko）成为球队新任主教练。斯超兹拉特莫拉夫采队解雇了主教练<strong>加拉德</strong>。斯甲胡门内队宣布由<strong>柳博米尔·莱特尔</strong>（Ľubomír Reiter）出任主帅。</li>\n<li>6月3日：斯乙联赛东区倒数第二轮结束，斯皮什新村队提前获得联赛冠军，升入下赛季的斯甲联赛。</li>\n<li>6月1日：扬·哈斯普拉卸任斯甲下库宾队主教练，就任从斯超降级的利普托夫斯基米库拉什队主教练。</li>\n<li>5月27日：斯洛伐克U19、U17和U16联赛结束。日利纳夺得U19、U17联赛冠军，将参加下赛季青年欧冠。鲁容贝罗克获得U16联赛冠军。</li>\n<li>5月26日：日利纳通过欧战资格附加赛获得欧协杯预选赛资格；兹拉特莫拉夫采在升降级附加赛次回合3-0大胜并逆转普雷绍夫塔特拉，保级成功。</li>\n</ul>\n","feature":true,"text":" 最近更新：2023年6月1日。本文争取每日更新，直到新赛季俱乐部欧战开始回到周更。 2023年世青赛专题：前瞻、球员、动态更新、比赛赛况 6月份国家队赛程（北京时间）见下| 比赛时间 | 对手 ||—|—|| 6月6日23:00 | 捷克U18 || 6月9日17:00 | 捷...","link":"","photos":[],"count_time":{"symbolsCount":"1.9k","symbolsTime":"2 mins."},"categories":[{"name":"简讯","slug":"简讯","count":92,"path":"api/categories/简讯.json"}],"tags":[{"name":"2023","slug":"2023","count":24,"path":"api/tags/2023.json"}],"toc":"<ol class=\"toc\"><li class=\"toc-item toc-level-2\"><a class=\"toc-link\" href=\"#%E5%93%88%E5%A7%86%E8%A5%BF%E5%85%8B%E5%AE%A3%E5%B8%83%E9%80%80%E5%BD%B9\"><span class=\"toc-text\">哈姆西克宣布退役</span></a></li><li class=\"toc-item toc-level-2\"><a class=\"toc-link\" href=\"#%E6%96%AF%E6%B4%9B%E4%BC%90%E5%85%8B%E5%90%84%E7%BA%A7%E5%9B%BD%E5%AE%B6%E9%98%9F%E7%AE%80%E8%AE%AF\"><span class=\"toc-text\">斯洛伐克各级国家队简讯</span></a></li><li class=\"toc-item toc-level-2\"><a class=\"toc-link\" href=\"#%E6%96%AF%E6%B4%9B%E4%BC%90%E5%85%8B%E6%B5%B7%E5%A4%96%E7%90%83%E5%91%98%E6%96%B0%E9%97%BB\"><span class=\"toc-text\">斯洛伐克海外球员新闻</span></a></li><li class=\"toc-item toc-level-2\"><a class=\"toc-link\" href=\"#%E6%96%AF%E6%B4%9B%E4%BC%90%E5%85%8B%E5%9B%BD%E5%86%85%E8%81%94%E8%B5%9B%E6%96%B0%E9%97%BB%EF%BC%88%E7%90%83%E5%91%98%EF%BC%89\"><span class=\"toc-text\">斯洛伐克国内联赛新闻（球员）</span></a></li><li class=\"toc-item toc-level-2\"><a class=\"toc-link\" href=\"#%E6%96%AF%E6%B4%9B%E4%BC%90%E5%85%8B%E5%9B%BD%E5%86%85%E8%81%94%E8%B5%9B%E6%96%B0%E9%97%BB%EF%BC%88%E7%90%83%E9%98%9F%E3%80%81%E6%95%99%E7%BB%83%EF%BC%89\"><span class=\"toc-text\">斯洛伐克国内联赛新闻（球队、教练）</span></a></li></ol>","author":{"name":"斯洛伐克足球狂做梦","slug":"blog-author","avatar":"/Images/icon.PNG","link":"https://svkfootballdream.github.io/","description":"中文斯洛伐克足球信息站","socials":{"github":"","twitter":"","stackoverflow":"","wechat":"","qq":"","weibo":"","zhihu":"","csdn":"","juejin":"","customs":{}}},"mapped":true,"prev_post":{"title":"2023-06：国家队信息汇总","uid":"f6455c4f8eb14c158054251b07d74c31","slug":"2023-06-nt-digest","date":"2023-05-31T23:26:50.000Z","updated":"2023-06-09T13:26:41.286Z","comments":true,"path":"api/articles/2023-06-nt-digest.json","keywords":null,"cover":null,"text":"6月份国家队赛程（北京时间）见下： 比赛时间 对手 6月6日23:00 捷克U18 6月9日17:00 捷克U18 6月15日23:30 匈牙利U21 6月18日02:45 冰岛（欧预赛） 6月20日23:30 奥地利U21 6月21日02:45 列支敦士登（欧预赛） 斯洛伐克国...","link":"","photos":[],"count_time":{"symbolsCount":"4.9k","symbolsTime":"4 mins."},"categories":[{"name":"斯洛伐克国家队","slug":"斯洛伐克国家队","count":43,"path":"api/categories/斯洛伐克国家队.json"}],"tags":[{"name":"比赛","slug":"比赛","count":25,"path":"api/tags/比赛.json"},{"name":"2023","slug":"2023","count":24,"path":"api/tags/2023.json"},{"name":"2024欧洲杯预选赛","slug":"2024欧洲杯预选赛","count":4,"path":"api/tags/2024欧洲杯预选赛.json"}],"author":{"name":"斯洛伐克足球狂做梦","slug":"blog-author","avatar":"/Images/icon.PNG","link":"https://svkfootballdream.github.io/","description":"中文斯洛伐克足球信息站","socials":{"github":"","twitter":"","stackoverflow":"","wechat":"","qq":"","weibo":"","zhihu":"","csdn":"","juejin":"","customs":{}}},"feature":true},"next_post":{"title":"2023年U20世青赛斯洛伐克队比赛赛况","uid":"df72c4d317b7cb0b5ac4ecd2946c2ef1","slug":"2023-u20-world-matches","date":"2023-05-17T03:32:51.000Z","updated":"2023-06-04T16:03:55.749Z","comments":true,"path":"api/articles/2023-u20-world-matches.json","keywords":null,"cover":"https://media.gettyimages.com/id/1258332992/photo/round-of-16-fifa-u-20-world-cup-argentina-2023.jpg?s=612x612&w=gi&k=20&c=Vqn8CPu0IJ5uycGiBMZjD4WVPimUn1JCs76O05ULJO0=","text":" 最近更新：2023年6月1日。2023年世青赛其他专题：前瞻、球员、动态更新 玉老田荒 八分之一决赛：斯洛伐克 1-5 哥伦比亚比赛简评老鲁斯纳克可能想在淘汰赛继续求稳，在首发阵容里安排了乌伊拉基和奥夫绍恩卡，增加了在三中卫和四后卫之间变化的可能。用乌伊拉基可能还是想用他的机动...","link":"","photos":[],"count_time":{"symbolsCount":"7k","symbolsTime":"6 mins."},"categories":[{"name":"斯洛伐克国家队","slug":"斯洛伐克国家队","count":43,"path":"api/categories/斯洛伐克国家队.json"}],"tags":[{"name":"2023","slug":"2023","count":24,"path":"api/tags/2023.json"},{"name":"2023年世青赛","slug":"2023年世青赛","count":4,"path":"api/tags/2023年世青赛.json"},{"name":"前瞻总结","slug":"前瞻总结","count":10,"path":"api/tags/前瞻总结.json"}],"author":{"name":"斯洛伐克足球狂做梦","slug":"blog-author","avatar":"/Images/icon.PNG","link":"https://svkfootballdream.github.io/","description":"中文斯洛伐克足球信息站","socials":{"github":"","twitter":"","stackoverflow":"","wechat":"","qq":"","weibo":"","zhihu":"","csdn":"","juejin":"","customs":{}}},"feature":true}}