{"name":"斯洛伐克足球文化","slug":"斯洛伐克足球文化","count":1,"postlist":[{"title":"再也没有“大卫对歌利亚”的足球故事了吗？","uid":"a81e3b6d6b97cc695108be1246303edb","slug":"2021-04-20-david-goliath","date":"2021-04-20T13:56:17.000Z","updated":"2021-06-22T04:58:25.743Z","comments":true,"path":"api/articles/2021-04-20-david-goliath.json","keywords":null,"cover":null,"text":"再也没有“大卫对歌利亚”的足球故事了吗？No more “David vs. Goliath” football stories?作者简介Zuzana Botiková（祖扎娜·博蒂科娃，ZB），斯洛伐克广播电视台（RTVS）国际部记者、英文主播，捷克马萨里克大学社会学博士。Ma...","link":"","photos":[],"count_time":{"symbolsCount":"9k","symbolsTime":"8 mins."},"categories":[{"name":"斯洛伐克足球文化","slug":"斯洛伐克足球文化","count":1,"path":"api/categories/斯洛伐克足球文化.json"}],"tags":[{"name":"2021","slug":"2021","count":23,"path":"api/tags/2021.json"},{"name":"采访","slug":"采访","count":3,"path":"api/tags/采访.json"}],"author":{"name":"斯洛伐克足球狂做梦","slug":"blog-author","avatar":"https://img-blog.csdnimg.cn/20210313122054101.png","link":"https://svkfootballdream.github.io/","description":"中文斯洛伐克足球信息站","socials":{"github":"","twitter":"","stackoverflow":"","wechat":"","qq":"","weibo":"","zhihu":"","csdn":"","juejin":"","customs":{}}}}]}